{
  "timestamp": 1783886278.8310416,
  "fetched_at": "2026-07-12T19:57:58.831044+00:00",
  "assets": [
    {
      "symbol": "BTC",
      "max_leverage": 40,
      "sz_decimals": 5,
      "volume_usd": 737353888.5630599,
      "tier": 1,
      "liquidity_score": 1.0
    },
    {
      "symbol": "ETH",
      "max_leverage": 25,
      "sz_decimals": 4,
      "volume_usd": 382088759.36035967,
      "tier": 1,
      "liquidity_score": 1.0
    },
    {
      "symbol": "HYPE",
      "max_leverage": 10,
      "sz_decimals": 2,
      "volume_usd": 170315272.4500601,
      "tier": 1,
      "liquidity_score": 1.0
    },
    {
      "symbol": "SOL",
      "max_leverage": 20,
      "sz_decimals": 2,
      "volume_usd": 144857014.01096985,
      "tier": 1,
      "liquidity_score": 1.0
    },
    {
      "symbol": "ZEC",
      "max_leverage": 10,
      "sz_decimals": 2,
      "volume_usd": 113572131.90910007,
      "tier": 1,
      "liquidity_score": 1.0
    },
    {
      "symbol": "CASHCAT",
      "max_leverage": 3,
      "sz_decimals": 0,
      "volume_usd": 44943976.53301,
      "tier": 2,
      "liquidity_score": 0.8
    },
    {
      "symbol": "LIT",
      "max_leverage": 5,
      "sz_decimals": 0,
      "volume_usd": 22347372.688100006,
      "tier": 2,
      "liquidity_score": 0.8
    },
    {
      "symbol": "WLD",
      "max_leverage": 10,
      "sz_decimals": 1,
      "volume_usd": 16916170.635436,
      "tier": 2,
      "liquidity_score": 0.8
    },
    {
      "symbol": "ARB",
      "max_leverage": 10,
      "sz_decimals": 1,
      "volume_usd": 14743317.63775099,
      "tier": 2,
      "liquidity_score": 0.8
    },
    {
      "symbol": "AAVE",
      "max_leverage": 10,
      "sz_decimals": 2,
      "volume_usd": 13494177.187600004,
      "tier": 2,
      "liquidity_score": 0.8
    },
    {
      "symbol": "XRP",
      "max_leverage": 20,
      "sz_decimals": 0,
      "volume_usd": 12424386.965799993,
      "tier": 2,
      "liquidity_score": 0.8
    },
    {
      "symbol": "UNI",
      "max_leverage": 10,
      "sz_decimals": 1,
      "volume_usd": 9407163.761580002,
      "tier": 3,
      "liquidity_score": 0.5
    },
    {
      "symbol": "FARTCOIN",
      "max_leverage": 10,
      "sz_decimals": 1,
      "volume_usd": 8736684.486043997,
      "tier": 3,
      "liquidity_score": 0.5
    },
    {
      "symbol": "NEAR",
      "max_leverage": 10,
      "sz_decimals": 1,
      "volume_usd": 6831081.416380005,
      "tier": 3,
      "liquidity_score": 0.5
    },
    {
      "symbol": "XMR",
      "max_leverage": 5,
      "sz_decimals": 3,
      "volume_usd": 5066362.445100002,
      "tier": 3,
      "liquidity_score": 0.5
    },
    {
      "symbol": "PUMP",
      "max_leverage": 10,
      "sz_decimals": 0,
      "volume_usd": 4859222.412488999,
      "tier": 4,
      "liquidity_score": 0.2
    },
    {
      "symbol": "BNB",
      "max_leverage": 10,
      "sz_decimals": 3,
      "volume_usd": 4835449.830129998,
      "tier": 4,
      "liquidity_score": 0.2
    },
    {
      "symbol": "SUI",
      "max_leverage": 10,
      "sz_decimals": 1,
      "volume_usd": 4635092.096714,
      "tier": 4,
      "liquidity_score": 0.2
    },
    {
      "symbol": "KAITO",
      "max_leverage": 5,
      "sz_decimals": 0,
      "volume_usd": 4473112.000460001,
      "tier": 4,
      "liquidity_score": 0.2
    },
    {
      "symbol": "ENA",
      "max_leverage": 10,
      "sz_decimals": 0,
      "volume_usd": 3975420.6681269985,
      "tier": 4,
      "liquidity_score": 0.2
    },
    {
      "symbol": "ADA",
      "max_leverage": 10,
      "sz_decimals": 0,
      "volume_usd": 3902804.4527400006,
      "tier": 4,
      "liquidity_score": 0.2
    },
    {
      "symbol": "VIRTUAL",
      "max_leverage": 5,
      "sz_decimals": 1,
      "volume_usd": 3612644.954489999,
      "tier": 4,
      "liquidity_score": 0.2
    },
    {
      "symbol": "DOGE",
      "max_leverage": 10,
      "sz_decimals": 0,
      "volume_usd": 3441004.9594049994,
      "tier": 4,
      "liquidity_score": 0.2
    },
    {
      "symbol": "AVAX",
      "max_leverage": 10,
      "sz_decimals": 2,
      "volume_usd": 2896332.9790669996,
      "tier": 4,
      "liquidity_score": 0.2
    },
    {
      "symbol": "XPL",
      "max_leverage": 10,
      "sz_decimals": 0,
      "volume_usd": 2840573.344681,
      "tier": 4,
      "liquidity_score": 0.2
    },
    {
      "symbol": "TRUMP",
      "max_leverage": 10,
      "sz_decimals": 1,
      "volume_usd": 2761744.714530001,
      "tier": 4,
      "liquidity_score": 0.2
    },
    {
      "symbol": "TAO",
      "max_leverage": 5,
      "sz_decimals": 3,
      "volume_usd": 2740752.2796199997,
      "tier": 4,
      "liquidity_score": 0.2
    },
    {
      "symbol": "VVV",
      "max_leverage": 3,
      "sz_decimals": 2,
      "volume_usd": 2448353.7122699996,
      "tier": 4,
      "liquidity_score": 0.2
    },
    {
      "symbol": "LINK",
      "max_leverage": 10,
      "sz_decimals": 1,
      "volume_usd": 2369843.1439500013,
      "tier": 4,
      "liquidity_score": 0.2
    },
    {
      "symbol": "kPEPE",
      "max_leverage": 10,
      "sz_decimals": 0,
      "volume_usd": 2230668.6587909996,
      "tier": 4,
      "liquidity_score": 0.2
    },
    {
      "symbol": "ETHFI",
      "max_leverage": 5,
      "sz_decimals": 1,
      "volume_usd": 2004815.839190999,
      "tier": 4,
      "liquidity_score": 0.2
    },
    {
      "symbol": "CRV",
      "max_leverage": 10,
      "sz_decimals": 1,
      "volume_usd": 1944631.5936830004,
      "tier": 4,
      "liquidity_score": 0.2
    },
    {
      "symbol": "JUP",
      "max_leverage": 10,
      "sz_decimals": 0,
      "volume_usd": 1821881.6199099987,
      "tier": 4,
      "liquidity_score": 0.2
    },
    {
      "symbol": "MORPHO",
      "max_leverage": 5,
      "sz_decimals": 1,
      "volume_usd": 1816120.702709999,
      "tier": 4,
      "liquidity_score": 0.2
    },
    {
      "symbol": "DOT",
      "max_leverage": 10,
      "sz_decimals": 1,
      "volume_usd": 1689030.8403710006,
      "tier": 4,
      "liquidity_score": 0.2
    },
    {
      "symbol": "ZRO",
      "max_leverage": 5,
      "sz_decimals": 1,
      "volume_usd": 1650399.9481820003,
      "tier": 4,
      "liquidity_score": 0.2
    },
    {
      "symbol": "GRAM",
      "max_leverage": 5,
      "sz_decimals": 0,
      "volume_usd": 1526492.1277000005,
      "tier": 4,
      "liquidity_score": 0.2
    },
    {
      "symbol": "LDO",
      "max_leverage": 5,
      "sz_decimals": 1,
      "volume_usd": 1521236.4010430004,
      "tier": 4,
      "liquidity_score": 0.2
    },
    {
      "symbol": "JTO",
      "max_leverage": 5,
      "sz_decimals": 0,
      "volume_usd": 1516657.8995,
      "tier": 4,
      "liquidity_score": 0.2
    },
    {
      "symbol": "XLM",
      "max_leverage": 5,
      "sz_decimals": 0,
      "volume_usd": 1503149.2127700003,
      "tier": 4,
      "liquidity_score": 0.2
    },
    {
      "symbol": "LTC",
      "max_leverage": 10,
      "sz_decimals": 2,
      "volume_usd": 1457569.1964499997,
      "tier": 4,
      "liquidity_score": 0.2
    },
    {
      "symbol": "PENGU",
      "max_leverage": 5,
      "sz_decimals": 0,
      "volume_usd": 1448586.3770699985,
      "tier": 4,
      "liquidity_score": 0.2
    },
    {
      "symbol": "ONDO",
      "max_leverage": 10,
      "sz_decimals": 0,
      "volume_usd": 1434007.1818000001,
      "tier": 4,
      "liquidity_score": 0.2
    },
    {
      "symbol": "MINA",
      "max_leverage": 3,
      "sz_decimals": 0,
      "volume_usd": 1364660.3596440002,
      "tier": 4,
      "liquidity_score": 0.2
    },
    {
      "symbol": "TIA",
      "max_leverage": 5,
      "sz_decimals": 1,
      "volume_usd": 1321088.232083,
      "tier": 4,
      "liquidity_score": 0.2
    },
    {
      "symbol": "MON",
      "max_leverage": 5,
      "sz_decimals": 0,
      "volume_usd": 1214535.2699680002,
      "tier": 4,
      "liquidity_score": 0.2
    },
    {
      "symbol": "EIGEN",
      "max_leverage": 5,
      "sz_decimals": 2,
      "volume_usd": 1173593.0210850004,
      "tier": 4,
      "liquidity_score": 0.2
    },
    {
      "symbol": "APT",
      "max_leverage": 10,
      "sz_decimals": 2,
      "volume_usd": 1157588.372659,
      "tier": 4,
      "liquidity_score": 0.2
    },
    {
      "symbol": "WLFI",
      "max_leverage": 5,
      "sz_decimals": 0,
      "volume_usd": 1105921.6058440001,
      "tier": 4,
      "liquidity_score": 0.2
    },
    {
      "symbol": "kBONK",
      "max_leverage": 10,
      "sz_decimals": 0,
      "volume_usd": 1018284.5797779999,
      "tier": 4,
      "liquidity_score": 0.2
    }
  ]
}